svetlanna/__init__.py
svetlanna/axes_math.py
svetlanna/clerk.py
svetlanna/detector.py
svetlanna/elements/__init__.py
svetlanna/elements/aperture.py
svetlanna/elements/diffractive_layer.py
svetlanna/elements/element.py
svetlanna/elements/free_space.py
svetlanna/elements/lens.py
svetlanna/elements/nonlinear_element.py
svetlanna/elements/reservoir.py
svetlanna/elements/slm.py
svetlanna/logging.py
svetlanna/networks/__init__.py
svetlanna/networks/autoencoder.py
svetlanna/networks/diffractive_conv.py
svetlanna/networks/diffractive_rnn.py
svetlanna/parameters.py
svetlanna/phase_retrieval_problem/__init__.py
svetlanna/phase_retrieval_problem/algorithms.py
svetlanna/phase_retrieval_problem/phase_retrieval.py
svetlanna/phase_retrieval_problem/phase_retrieval_result.py
svetlanna/setup.py
svetlanna/simulation_parameters.py
svetlanna/specs/__init__.py
svetlanna/specs/specs.py
svetlanna/specs/specs_writer.py
svetlanna/transforms.py
svetlanna/units.py
svetlanna/visualization/__init__.py
svetlanna/visualization/static/setup_widget.css
svetlanna/visualization/static/specs_widget.js
svetlanna/visualization/static/stepwise_forward_widget.js
svetlanna/visualization/templates/widget_aperture.html.jinja
svetlanna/visualization/templates/widget_default.html.jinja
svetlanna/visualization/templates/widget_diffractive_layer.html.jinja
svetlanna/visualization/templates/widget_free_space.html.jinja
svetlanna/visualization/templates/widget_lens.html.jinja
svetlanna/visualization/templates/widget_linear_setup.html.jinja
svetlanna/visualization/templates/widget_reservoir.html.jinja
svetlanna/visualization/templates/widget_structure_container.html.jinja
svetlanna/visualization/widgets.py
svetlanna/wavefront.py
svetlanna-1.0.4.dist-info/METADATA
svetlanna-1.0.4.dist-info/WHEEL
svetlanna-1.0.4.dist-info/licenses/LICENSE
svetlanna-1.0.4.dist-info/RECORD
