Metadata-Version: 2.4
Name: svetlanna
Version: 1.0.4
Summary: SVETlANNa is an open-source Python library for simulation of free-space optical set-ups and neuromorphic systems such as Diffractive Neural Networks.
License: Mozilla Public License Version 2.0
License-File: LICENSE
Keywords: optical neural network,diffractive neural network,pytorch,optical beam,optical setup,diffractive element,spatial light modulator
Author: Alexey A. Shcherbakov
Author-email: cplab@metalab.ifmo.ru
Requires-Python: >=3.11.0,<3.12
Classifier: Development Status :: 5 - Production/Stable
Classifier: Intended Audience :: Developers
Classifier: Intended Audience :: Science/Research
Classifier: Intended Audience :: Education
Classifier: Topic :: Software Development :: Libraries
Classifier: Topic :: Scientific/Engineering :: Artificial Intelligence
Classifier: Topic :: Scientific/Engineering :: Physics
Classifier: License :: OSI Approved :: Mozilla Public License 2.0 (MPL 2.0)
Classifier: Programming Language :: Python :: 3.11
Provides-Extra: pandas
Requires-Dist: anywidget (>=0.9.13,<0.10.0)
Requires-Dist: jinja2 (>=3.1.6,<4.0.0)
Requires-Dist: matplotlib (<3.9.2)
Requires-Dist: numpy (<2.0)
Requires-Dist: pandas (>=2.2.3,<3.0.0) ; extra == "pandas"
Project-URL: Documentation, https://compphyslab.github.io/SVETlANNa/
Project-URL: Repository, https://github.com/CompPhysLab/SVETlANNa
